looo.py-2018.1.data/scripts/loopy
loopy/__init__.py
loopy/__main__.py
loopy/_git_rev.py
loopy/auto_test.py
loopy/check.py
loopy/cli.py
loopy/compiled.py
loopy/diagnostic.py
loopy/expression.py
loopy/ipython_ext.py
loopy/isl_helpers.py
loopy/loop.py
loopy/match.py
loopy/maxima.py
loopy/options.py
loopy/preprocess.py
loopy/statistics.py
loopy/symbolic.py
loopy/tools.py
loopy/type_inference.py
loopy/types.py
loopy/version.py
loopy/codegen/__init__.py
loopy/codegen/bounds.py
loopy/codegen/control.py
loopy/codegen/instruction.py
loopy/codegen/loop.py
loopy/codegen/result.py
loopy/frontend/__init__.py
loopy/frontend/fortran/__init__.py
loopy/frontend/fortran/diagnostic.py
loopy/frontend/fortran/expression.py
loopy/frontend/fortran/translator.py
loopy/frontend/fortran/tree.py
loopy/kernel/__init__.py
loopy/kernel/array.py
loopy/kernel/creation.py
loopy/kernel/data.py
loopy/kernel/function_interface.py
loopy/kernel/instruction.py
loopy/kernel/tools.py
loopy/library/__init__.py
loopy/library/function.py
loopy/library/random123.py
loopy/library/reduction.py
loopy/schedule/__init__.py
loopy/schedule/device_mapping.py
loopy/schedule/tools.py
loopy/target/__init__.py
loopy/target/cuda.py
loopy/target/execution.py
loopy/target/ispc.py
loopy/target/numba.py
loopy/target/opencl.py
loopy/target/pyopencl.py
loopy/target/pyopencl_execution.py
loopy/target/python.py
loopy/target/c/__init__.py
loopy/target/c/c_execution.py
loopy/target/c/codegen/__init__.py
loopy/target/c/codegen/expression.py
loopy/transform/__init__.py
loopy/transform/add_barrier.py
loopy/transform/arithmetic.py
loopy/transform/array_buffer_map.py
loopy/transform/batch.py
loopy/transform/buffer.py
loopy/transform/data.py
loopy/transform/diff.py
loopy/transform/fusion.py
loopy/transform/iname.py
loopy/transform/instruction.py
loopy/transform/pack_and_unpack_args.py
loopy/transform/padding.py
loopy/transform/parameter.py
loopy/transform/precompute.py
loopy/transform/privatize.py
loopy/transform/register_callable.py
looo.py-2018.1.dist-info/METADATA
looo.py-2018.1.dist-info/WHEEL
looo.py-2018.1.dist-info/dependency_links.txt
looo.py-2018.1.dist-info/top_level.txt
looo.py-2018.1.dist-info/RECORD
